README.md
setup.py
barrak_hello_world.egg-info/PKG-INFO
barrak_hello_world.egg-info/SOURCES.txt
barrak_hello_world.egg-info/dependency_links.txt
barrak_hello_world.egg-info/top_level.txt
sample_package/__init__.py
sample_package/sample.py